Metadata-Version: 1.1
Name: django-context
Version: 0.1.0
Summary: Django app to have an ability to set custom context in a main application
Home-page: https://github.com/GregEremeev/django-django_context
Author: Greg Eremeev
Author-email: gregory.eremeev@gmail.com
License: BSD
Platform: UNKNOWN
Classifier: Environment :: Web Environment
Classifier: Framework :: Django :: 1.11
Classifier: Framework :: Django :: 2.1
Classifier: Intended Audience :: Developers
Classifier: License :: OSI Approved :: BSD License
Classifier: Operating System :: OS Independent
Classifier: Programming Language :: Python :: 3.5
Classifier: Programming Language :: Python :: 3.6
Classifier: Programming Language :: Python :: 3.7
Classifier: Topic :: Internet :: WWW/HTTP
